{
    "nombre":"Pancho",
    "especie":"Gato",
    "raza":"Mestizo",
    "sexo":"Macho",
    "color":"Atigrado",
    "edad":1.5,
    "propietario":{
        "tipoIdentificacion":"CE",
        "nombre":"Roberto",
        "apellido":"Pineda",
        "direccion":"Lima",
        "telefono":"916730940"
    }
    ,
    "vacunas":[
        "TripleFelina",
        "Antirabica"
    ]
}










{
    "nombre":"Turron",
    "especie":"Perro",
    "raza":"Mestizo",
    "sexo":"Macho",
    "color":"Negro",
    "edad":1,
    "propietario":{
        "tipoIdentificacion":"DNI",
        "nombre":"Leslie",
        "apellido":"Tapara",
        "direccion":"Lima",
        "telefono":"937699394"
    }
    ,
    "vacunas":[
        "Rabia"
        
    ]
}
{
    "nombre":"Lana",
    "especie":"Gato",
    "raza":"Mestizo",
    "sexo":"Hembra",
    "color":"Atigrado",
    "edad":0.08,
    "propietario":{
        "tipoIdentificacion":"DNI",
        "nombre":"Leslie",
        "apellido":"Tapara",
        "direccion":"Lima",
        "telefono":"937699394"
    }
    ,
    "vacunas":[
        "Rabia",
        
    ]
}


{
    "nombre":"Selina",
    "especie":"Gato",
    "raza":"Mestizo",
    "sexo":"Hembra",
    "color":"Blanco",
    "edad":4,
    "propietario":{
        "tipoIdentificacion":"CE",
        "nombre":"Roberto",
        "apellido":"Pineda",
        "direccion":"Lima",
        "telefono":"916730940"
    }
    ,
    "vacunas":[
        "TripleFelina",
        "Rabia"
    ]
}

{
    "nombre":"Luna",
    "especie":"Perro",
    "raza":"Mestizo",
    "sexo":"Hembra",
    "color":"Negro",
    "edad":4,
    "propietario":{
        "tipoIdentificacion":"DNI",
        "nombre":"Leslie",
        "apellido":"Tapara",
        "direccion":"Lima",
        "telefono":"937699394"
    }
    ,
    "vacunas":[
        "Rabia"
        
    ]
}